cryo_sam/__init__.py
cryo_sam/cryo_sam.py
cryo_sam/structures.py
cryo_sam/utils.py
cryo_sam-0.0.82.dist-info/LICENSE.txt
cryo_sam-0.0.82.dist-info/METADATA
cryo_sam-0.0.82.dist-info/WHEEL
cryo_sam-0.0.82.dist-info/top_level.txt
cryo_sam-0.0.82.dist-info/RECORD
