Metadata-Version: 2.1
Name: cryo-sam
Version: 0.0.82
Summary: A tool to find cryo-em targets for cyro-em automation building on foundation ML models.
Author-email: James Rodgers <jms.rdgrs@gmail.com>
License: MIT
Classifier: Environment :: GPU :: NVIDIA CUDA
Classifier: Topic :: Scientific/Engineering :: Image Processing
Requires-Python: >=3.8
License-File: LICENSE.txt
Requires-Dist: matplotlib
Requires-Dist: numpy
Requires-Dist: opencv-python
Requires-Dist: opencv-python-headless
Requires-Dist: segment-anything
Requires-Dist: torch
